sc_runner/__init__.py
sc_runner/cli.py
sc_runner/cloud_meta.py
sc_runner/data.py
sc_runner/runner.py
sc_runner/resources/__init__.py
sc_runner/resources/alicloud.py
sc_runner/resources/aws.py
sc_runner/resources/azure.py
sc_runner/resources/base.py
sc_runner/resources/gcp.py
sc_runner/resources/hcloud.py
sc_runner/resources/ovh.py
sc_runner/resources/upcloud.py
sparecores_runner-0.0.39.dist-info/licenses/LICENSE
sparecores_runner-0.0.39.dist-info/METADATA
sparecores_runner-0.0.39.dist-info/WHEEL
sparecores_runner-0.0.39.dist-info/entry_points.txt
sparecores_runner-0.0.39.dist-info/top_level.txt
sparecores_runner-0.0.39.dist-info/RECORD
