Metadata-Version: 2.4
Name: sparecores-runner
Version: 0.0.39
Summary: Start and manage cloud instances.
Author: Attila Nagy, Gergely Daroczi
Maintainer-email: Spare Cores team <pkg@sparecores.com>
Project-URL: repository, https://github.com/SpareCores/sc-runner
Project-URL: issues, https://github.com/SpareCores/sc-runner/issues
Project-URL: documentation, https://sparecores.github.io/sc-runner/
Project-URL: homepage, https://sparecores.com
Keywords: cloud,compute
Classifier: Programming Language :: Python :: 3
Classifier: License :: OSI Approved :: Mozilla Public License 2.0 (MPL 2.0)
Classifier: Operating System :: OS Independent
Classifier: Development Status :: 3 - Alpha
Requires-Python: >=3.9
License-File: LICENSE
Requires-Dist: click
Requires-Dist: pulumi
Requires-Dist: pulumi-alicloud
Requires-Dist: pulumi-aws
Requires-Dist: pulumi-azure-native
Requires-Dist: pulumi-gcp
Requires-Dist: pulumi-hcloud
Requires-Dist: pulumi-ovh
Requires-Dist: pulumi-upcloud
Requires-Dist: requests
Requires-Dist: sentry-sdk
Requires-Dist: sparecores-crawler>=0.2.1
Requires-Dist: sparecores-data>=0.2.1
Requires-Dist: sqlmodel
Dynamic: license-file
